fasega/__init__.py
fasega/bible.py
fasega/birthdayAnimation.py
fasega/data/__init__.py
fasega/data/affirmations.txt
Fasega-0.0.1.dist-info/METADATA
Fasega-0.0.1.dist-info/WHEEL
Fasega-0.0.1.dist-info/entry_points.txt
Fasega-0.0.1.dist-info/top_level.txt
Fasega-0.0.1.dist-info/RECORD
