Metadata-Version: 2.1
Name: Fasega
Version: 0.0.1
Summary: Happy birthday! 😘😍🥰💝
Home-page: https://gitlab.com/agerma/fasega
Author: Abelether Germa
Author-email: hithere@damngirl.com
License: UNKNOWN
Platform: UNKNOWN
Classifier: Programming Language :: Python :: 3.7
Classifier: License :: OSI Approved :: MIT License
Classifier: Operating System :: OS Independent
Requires-Dist: click
Requires-Dist: setuptools
Requires-Dist: pyfiglet
Requires-Dist: requests
Requires-Dist: asciimatics
